suteado/main.py
suteado-1.1.dist-info/METADATA
suteado-1.1.dist-info/WHEEL
suteado-1.1.dist-info/top_level.txt
suteado-1.1.dist-info/RECORD
