Metadata-Version: 2.2
Name: suteado
Version: 1.1
Summary: m.kuku.luで使える捨てアドぽいぽいの非公式API
Home-page: https://github.com/milypy/suteado/
Download-URL: https://github.com/milypy/suteado/
Author: mily
Author-email: goshoahiru0323@gmail.com
Maintainer: mily
Maintainer-email: goshoahiru0323@gmail.com
License: MIT
Keywords: suteadopoipoi suteado mail freemail
Classifier: License :: OSI Approved :: MIT License
Classifier: Programming Language :: Python :: 3.1
Requires-Dist: requests
Dynamic: author
Dynamic: author-email
Dynamic: classifier
Dynamic: description
Dynamic: description-content-type
Dynamic: download-url
Dynamic: home-page
Dynamic: keywords
Dynamic: license
Dynamic: maintainer
Dynamic: maintainer-email
Dynamic: requires-dist
Dynamic: summary
